[
  {
    "results": [
      {
        "town_list": [
          {
            "ORDERNAME": "11010",
            "CODE": 1101,
            "NAME": "종로구"
          },
          {
            "ORDERNAME": "11020",
            "CODE": 1102,
            "NAME": "중구(서울)"
          },
          {
            "ORDERNAME": "11030",
            "CODE": 1103,
            "NAME": "동대문갑구"
          },
          {
            "ORDERNAME": "11040",
            "CODE": 1104,
            "NAME": "동대문을구"
          },
          {
            "ORDERNAME": "11050",
            "CODE": 1105,
            "NAME": "성동갑구"
          },
          {
            "ORDERNAME": "11060",
            "CODE": 1106,
            "NAME": "성동을구"
          },
          {
            "ORDERNAME": "11070",
            "CODE": 1107,
            "NAME": "성동병구"
          },
          {
            "ORDERNAME": "11080",
            "CODE": 1108,
            "NAME": "성북갑구"
          },
          {
            "ORDERNAME": "11090",
            "CODE": 1109,
            "NAME": "성북을구"
          },
          {
            "ORDERNAME": "11100",
            "CODE": 1110,
            "NAME": "성북병구"
          },
          {
            "ORDERNAME": "11110",
            "CODE": 1111,
            "NAME": "서대문갑구"
          },
          {
            "ORDERNAME": "11120",
            "CODE": 1112,
            "NAME": "서대문을구"
          },
          {
            "ORDERNAME": "11130",
            "CODE": 1113,
            "NAME": "서대문병구"
          },
          {
            "ORDERNAME": "11140",
            "CODE": 1114,
            "NAME": "마포구"
          },
          {
            "ORDERNAME": "11150",
            "CODE": 1115,
            "NAME": "용산구"
          },
          {
            "ORDERNAME": "11160",
            "CODE": 1116,
            "NAME": "영등포갑구"
          },
          {
            "ORDERNAME": "11170",
            "CODE": 1117,
            "NAME": "영등포을구"
          },
          {
            "ORDERNAME": "11180",
            "CODE": 1118,
            "NAME": "영등포병구"
          },
          {
            "ORDERNAME": "11190",
            "CODE": 1119,
            "NAME": "영등포정구"
          }
        ],
        "town_dict": {
          "서대문병구": 1113,
          "서대문을구": 1112,
          "성동병구": 1107,
          "마포구": 1114,
          "영등포갑구": 1116,
          "성북병구": 1110,
          "성북갑구": 1108,
          "영등포정구": 1119,
          "용산구": 1115,
          "성동갑구": 1105,
          "종로구": 1101,
          "중구(서울)": 1102,
          "영등포병구": 1118,
          "성북을구": 1109,
          "동대문을구": 1104,
          "성동을구": 1106,
          "동대문갑구": 1103,
          "영등포을구": 1117,
          "서대문갑구": 1111
        },
        "city_name": "서울",
        "city_code": 11
      },
      {
        "town_list": [
          {
            "ORDERNAME": "26010",
            "CODE": 2601,
            "NAME": "중구"
          },
          {
            "ORDERNAME": "26020",
            "CODE": 2602,
            "NAME": "서구"
          },
          {
            "ORDERNAME": "26030",
            "CODE": 2603,
            "NAME": "동구"
          },
          {
            "ORDERNAME": "26040",
            "CODE": 2604,
            "NAME": "영도구"
          },
          {
            "ORDERNAME": "26050",
            "CODE": 2605,
            "NAME": "부산진갑"
          },
          {
            "ORDERNAME": "26060",
            "CODE": 2606,
            "NAME": "부산진을"
          },
          {
            "ORDERNAME": "26070",
            "CODE": 2607,
            "NAME": "동래갑"
          },
          {
            "ORDERNAME": "26080",
            "CODE": 2608,
            "NAME": "동래을"
          }
        ],
        "town_dict": {
          "서구": 2602,
          "부산진갑": 2605,
          "동래을": 2608,
          "동래갑": 2607,
          "동구": 2603,
          "부산진을": 2606,
          "영도구": 2604,
          "중구": 2601
        },
        "city_name": "부산",
        "city_code": 26
      },
      {
        "town_list": [
          {
            "ORDERNAME": "41010",
            "CODE": 4101,
            "NAME": "인천시동구"
          },
          {
            "ORDERNAME": "41020",
            "CODE": 4102,
            "NAME": "인천시중구"
          },
          {
            "ORDERNAME": "41030",
            "CODE": 4103,
            "NAME": "인천시남구"
          },
          {
            "ORDERNAME": "41040",
            "CODE": 4104,
            "NAME": "인천시북구"
          },
          {
            "ORDERNAME": "41051",
            "CODE": 41051,
            "NAME": "수원시"
          },
          {
            "ORDERNAME": "41061",
            "CODE": 41061,
            "NAME": "의정부시"
          },
          {
            "ORDERNAME": "41072",
            "CODE": 41072,
            "NAME": "양주군"
          },
          {
            "ORDERNAME": "41082",
            "CODE": 41082,
            "NAME": "이천군"
          },
          {
            "ORDERNAME": "41092",
            "CODE": 41092,
            "NAME": "광주군"
          },
          {
            "ORDERNAME": "41102",
            "CODE": 41102,
            "NAME": "포천군"
          },
          {
            "ORDERNAME": "41112",
            "CODE": 41112,
            "NAME": "연천군"
          },
          {
            "ORDERNAME": "41122",
            "CODE": 41122,
            "NAME": "가평군"
          },
          {
            "ORDERNAME": "41132",
            "CODE": 41132,
            "NAME": "여주군"
          },
          {
            "ORDERNAME": "41142",
            "CODE": 41142,
            "NAME": "양평군"
          },
          {
            "ORDERNAME": "41152",
            "CODE": 41152,
            "NAME": "안성군"
          },
          {
            "ORDERNAME": "41162",
            "CODE": 41162,
            "NAME": "용인군"
          },
          {
            "ORDERNAME": "41172",
            "CODE": 41172,
            "NAME": "평택군"
          },
          {
            "ORDERNAME": "41182",
            "CODE": 41182,
            "NAME": "화성군"
          },
          {
            "ORDERNAME": "41192",
            "CODE": 41192,
            "NAME": "파주군"
          },
          {
            "ORDERNAME": "41202",
            "CODE": 41202,
            "NAME": "고양군"
          },
          {
            "ORDERNAME": "41212",
            "CODE": 41212,
            "NAME": "강화군"
          },
          {
            "ORDERNAME": "41222",
            "CODE": 41222,
            "NAME": "김포군"
          },
          {
            "ORDERNAME": "41232",
            "CODE": 41232,
            "NAME": "시흥군"
          },
          {
            "ORDERNAME": "41242",
            "CODE": 41242,
            "NAME": "부천군"
          },
          {
            "ORDERNAME": "41252",
            "CODE": 41252,
            "NAME": "옹진군"
          }
        ],
        "town_dict": {
          "시흥군": 41232,
          "인천시동구": 4101,
          "여주군": 41132,
          "양주군": 41072,
          "용인군": 41162,
          "인천시북구": 4104,
          "안성군": 41152,
          "이천군": 41082,
          "의정부시": 41061,
          "수원시": 41051,
          "파주군": 41192,
          "고양군": 41202,
          "평택군": 41172,
          "화성군": 41182,
          "연천군": 41112,
          "옹진군": 41252,
          "김포군": 41222,
          "부천군": 41242,
          "강화군": 41212,
          "양평군": 41142,
          "가평군": 41122,
          "포천군": 41102,
          "광주군": 41092,
          "인천시남구": 4103,
          "인천시중구": 4102
        },
        "city_name": "경기",
        "city_code": 41
      },
      {
        "town_list": [
          {
            "ORDERNAME": "42011",
            "CODE": 42011,
            "NAME": "춘천시"
          },
          {
            "ORDERNAME": "42022",
            "CODE": 42022,
            "NAME": "춘성군"
          },
          {
            "ORDERNAME": "42031",
            "CODE": 42031,
            "NAME": "원주시"
          },
          {
            "ORDERNAME": "42042",
            "CODE": 42042,
            "NAME": "원성군"
          },
          {
            "ORDERNAME": "42051",
            "CODE": 42051,
            "NAME": "강릉시"
          },
          {
            "ORDERNAME": "42062",
            "CODE": 42062,
            "NAME": "명주군"
          },
          {
            "ORDERNAME": "42072",
            "CODE": 42072,
            "NAME": "홍천군"
          },
          {
            "ORDERNAME": "42082",
            "CODE": 42082,
            "NAME": "인제군"
          },
          {
            "ORDERNAME": "42092",
            "CODE": 42092,
            "NAME": "영월군"
          },
          {
            "ORDERNAME": "42102",
            "CODE": 42102,
            "NAME": "정선군"
          },
          {
            "ORDERNAME": "42112",
            "CODE": 42112,
            "NAME": "화천군"
          },
          {
            "ORDERNAME": "42122",
            "CODE": 42122,
            "NAME": "철원군"
          },
          {
            "ORDERNAME": "42132",
            "CODE": 42132,
            "NAME": "양구군"
          },
          {
            "ORDERNAME": "42141",
            "CODE": 42141,
            "NAME": "속초시"
          },
          {
            "ORDERNAME": "42152",
            "CODE": 42152,
            "NAME": "양양군"
          },
          {
            "ORDERNAME": "42162",
            "CODE": 42162,
            "NAME": "고성군"
          },
          {
            "ORDERNAME": "42172",
            "CODE": 42172,
            "NAME": "횡성군"
          },
          {
            "ORDERNAME": "42182",
            "CODE": 42182,
            "NAME": "평창군"
          },
          {
            "ORDERNAME": "42192",
            "CODE": 42192,
            "NAME": "삼척군"
          }
        ],
        "town_dict": {
          "정선군": 42102,
          "영월군": 42092,
          "고성군": 42162,
          "춘성군": 42022,
          "평창군": 42182,
          "속초시": 42141,
          "화천군": 42112,
          "횡성군": 42172,
          "삼척군": 42192,
          "강릉시": 42051,
          "원성군": 42042,
          "홍천군": 42072,
          "양양군": 42152,
          "양구군": 42132,
          "인제군": 42082,
          "춘천시": 42011,
          "원주시": 42031,
          "철원군": 42122,
          "명주군": 42062
        },
        "city_name": "강원",
        "city_code": 42
      },
      {
        "town_list": [
          {
            "ORDERNAME": "43011",
            "CODE": 43011,
            "NAME": "청주시"
          },
          {
            "ORDERNAME": "43022",
            "CODE": 43022,
            "NAME": "청원군"
          },
          {
            "ORDERNAME": "43031",
            "CODE": 43031,
            "NAME": "충주시"
          },
          {
            "ORDERNAME": "43042",
            "CODE": 43042,
            "NAME": "중원군"
          },
          {
            "ORDERNAME": "43052",
            "CODE": 43052,
            "NAME": "옥천군"
          },
          {
            "ORDERNAME": "43062",
            "CODE": 43062,
            "NAME": "보은군"
          },
          {
            "ORDERNAME": "43072",
            "CODE": 43072,
            "NAME": "괴산군"
          },
          {
            "ORDERNAME": "43082",
            "CODE": 43082,
            "NAME": "영동군"
          },
          {
            "ORDERNAME": "43092",
            "CODE": 43092,
            "NAME": "음성군"
          },
          {
            "ORDERNAME": "43102",
            "CODE": 43102,
            "NAME": "진천군"
          },
          {
            "ORDERNAME": "43112",
            "CODE": 43112,
            "NAME": "제천군"
          },
          {
            "ORDERNAME": "43122",
            "CODE": 43122,
            "NAME": "단양군"
          }
        ],
        "town_dict": {
          "진천군": 43102,
          "청주시": 43011,
          "옥천군": 43052,
          "충주시": 43031,
          "보은군": 43062,
          "괴산군": 43072,
          "영동군": 43082,
          "단양군": 43122,
          "청원군": 43022,
          "음성군": 43092,
          "제천군": 43112,
          "중원군": 43042
        },
        "city_name": "충북",
        "city_code": 43
      },
      {
        "town_list": [
          {
            "ORDERNAME": "44011",
            "CODE": 44011,
            "NAME": "대전시갑"
          },
          {
            "ORDERNAME": "44021",
            "CODE": 44021,
            "NAME": "대전시을"
          },
          {
            "ORDERNAME": "44032",
            "CODE": 44032,
            "NAME": "대덕군"
          },
          {
            "ORDERNAME": "44042",
            "CODE": 44042,
            "NAME": "연기군"
          },
          {
            "ORDERNAME": "44052",
            "CODE": 44052,
            "NAME": "공주군"
          },
          {
            "ORDERNAME": "44062",
            "CODE": 44062,
            "NAME": "논산군"
          },
          {
            "ORDERNAME": "44072",
            "CODE": 44072,
            "NAME": "부여군"
          },
          {
            "ORDERNAME": "44082",
            "CODE": 44082,
            "NAME": "서천군"
          },
          {
            "ORDERNAME": "44092",
            "CODE": 44092,
            "NAME": "보령군"
          },
          {
            "ORDERNAME": "44102",
            "CODE": 44102,
            "NAME": "홍성군"
          },
          {
            "ORDERNAME": "44112",
            "CODE": 44112,
            "NAME": "청양군"
          },
          {
            "ORDERNAME": "44122",
            "CODE": 44122,
            "NAME": "예산군"
          },
          {
            "ORDERNAME": "44132",
            "CODE": 44132,
            "NAME": "서산군"
          },
          {
            "ORDERNAME": "44142",
            "CODE": 44142,
            "NAME": "당진군"
          },
          {
            "ORDERNAME": "44152",
            "CODE": 44152,
            "NAME": "아산군"
          },
          {
            "ORDERNAME": "44161",
            "CODE": 44161,
            "NAME": "천안군"
          },
          {
            "ORDERNAME": "44172",
            "CODE": 44172,
            "NAME": "천원군"
          },
          {
            "ORDERNAME": "44182",
            "CODE": 44182,
            "NAME": "금산군"
          }
        ],
        "town_dict": {
          "부여군": 44072,
          "서산군": 44132,
          "공주군": 44052,
          "금산군": 44182,
          "논산군": 44062,
          "천원군": 44172,
          "홍성군": 44102,
          "청양군": 44112,
          "보령군": 44092,
          "대전시갑": 44011,
          "예산군": 44122,
          "당진군": 44142,
          "아산군": 44152,
          "대전시을": 44021,
          "대덕군": 44032,
          "서천군": 44082,
          "천안군": 44161,
          "연기군": 44042
        },
        "city_name": "충남",
        "city_code": 44
      },
      {
        "town_list": [
          {
            "ORDERNAME": "45011",
            "CODE": 45011,
            "NAME": "전주시"
          },
          {
            "ORDERNAME": "45021",
            "CODE": 45021,
            "NAME": "군산시"
          },
          {
            "ORDERNAME": "45032",
            "CODE": 45032,
            "NAME": "옥구군"
          },
          {
            "ORDERNAME": "45041",
            "CODE": 45041,
            "NAME": "이리시"
          },
          {
            "ORDERNAME": "45052",
            "CODE": 45052,
            "NAME": "익산군"
          },
          {
            "ORDERNAME": "45062",
            "CODE": 45062,
            "NAME": "완주군"
          },
          {
            "ORDERNAME": "45072",
            "CODE": 45072,
            "NAME": "진안군"
          },
          {
            "ORDERNAME": "45082",
            "CODE": 45082,
            "NAME": "장수군"
          },
          {
            "ORDERNAME": "45092",
            "CODE": 45092,
            "NAME": "무주군"
          },
          {
            "ORDERNAME": "45102",
            "CODE": 45102,
            "NAME": "임실군"
          },
          {
            "ORDERNAME": "45112",
            "CODE": 45112,
            "NAME": "순창군"
          },
          {
            "ORDERNAME": "45122",
            "CODE": 45122,
            "NAME": "남원군"
          },
          {
            "ORDERNAME": "45132",
            "CODE": 45132,
            "NAME": "정읍군"
          },
          {
            "ORDERNAME": "45142",
            "CODE": 45142,
            "NAME": "고창군"
          },
          {
            "ORDERNAME": "45152",
            "CODE": 45152,
            "NAME": "부안군"
          },
          {
            "ORDERNAME": "45162",
            "CODE": 45162,
            "NAME": "김제군"
          }
        ],
        "town_dict": {
          "익산군": 45052,
          "정읍군": 45132,
          "옥구군": 45032,
          "전주시": 45011,
          "부안군": 45152,
          "이리시": 45041,
          "임실군": 45102,
          "남원군": 45122,
          "고창군": 45142,
          "순창군": 45112,
          "무주군": 45092,
          "김제군": 45162,
          "진안군": 45072,
          "완주군": 45062,
          "군산시": 45021,
          "장수군": 45082
        },
        "city_name": "전북",
        "city_code": 45
      },
      {
        "town_list": [
          {
            "ORDERNAME": "46011",
            "CODE": 46011,
            "NAME": "광주시갑구"
          },
          {
            "ORDERNAME": "46021",
            "CODE": 46021,
            "NAME": "광주시을구"
          },
          {
            "ORDERNAME": "46031",
            "CODE": 46031,
            "NAME": "목포시"
          },
          {
            "ORDERNAME": "46041",
            "CODE": 46041,
            "NAME": "여수시"
          },
          {
            "ORDERNAME": "46052",
            "CODE": 46052,
            "NAME": "여천군"
          },
          {
            "ORDERNAME": "46061",
            "CODE": 46061,
            "NAME": "순천시"
          },
          {
            "ORDERNAME": "46072",
            "CODE": 46072,
            "NAME": "승주군"
          },
          {
            "ORDERNAME": "46082",
            "CODE": 46082,
            "NAME": "장성군"
          },
          {
            "ORDERNAME": "46092",
            "CODE": 46092,
            "NAME": "담양군"
          },
          {
            "ORDERNAME": "46102",
            "CODE": 46102,
            "NAME": "화순군"
          },
          {
            "ORDERNAME": "46112",
            "CODE": 46112,
            "NAME": "곡성군"
          },
          {
            "ORDERNAME": "46122",
            "CODE": 46122,
            "NAME": "광양군"
          },
          {
            "ORDERNAME": "46132",
            "CODE": 46132,
            "NAME": "구례군"
          },
          {
            "ORDERNAME": "46142",
            "CODE": 46142,
            "NAME": "고흥군"
          },
          {
            "ORDERNAME": "46152",
            "CODE": 46152,
            "NAME": "보성군"
          },
          {
            "ORDERNAME": "46162",
            "CODE": 46162,
            "NAME": "장흥군"
          },
          {
            "ORDERNAME": "46172",
            "CODE": 46172,
            "NAME": "영암군"
          },
          {
            "ORDERNAME": "46182",
            "CODE": 46182,
            "NAME": "강진군"
          },
          {
            "ORDERNAME": "46192",
            "CODE": 46192,
            "NAME": "완도군"
          },
          {
            "ORDERNAME": "46202",
            "CODE": 46202,
            "NAME": "해남군"
          },
          {
            "ORDERNAME": "46212",
            "CODE": 46212,
            "NAME": "무안군"
          },
          {
            "ORDERNAME": "46222",
            "CODE": 46222,
            "NAME": "신안군"
          },
          {
            "ORDERNAME": "46232",
            "CODE": 46232,
            "NAME": "나주군"
          },
          {
            "ORDERNAME": "46242",
            "CODE": 46242,
            "NAME": "광산군"
          },
          {
            "ORDERNAME": "46252",
            "CODE": 46252,
            "NAME": "영광군"
          },
          {
            "ORDERNAME": "46262",
            "CODE": 46262,
            "NAME": "함평군"
          },
          {
            "ORDERNAME": "46272",
            "CODE": 46272,
            "NAME": "진도군"
          }
        ],
        "town_dict": {
          "장성군": 46082,
          "나주군": 46232,
          "화순군": 46102,
          "진도군": 46272,
          "담양군": 46092,
          "순천시": 46061,
          "보성군": 46152,
          "광양군": 46122,
          "곡성군": 46112,
          "무안군": 46212,
          "승주군": 46072,
          "해남군": 46202,
          "장흥군": 46162,
          "광주시갑구": 46011,
          "광산군": 46242,
          "영암군": 46172,
          "광주시을구": 46021,
          "여천군": 46052,
          "고흥군": 46142,
          "목포시": 46031,
          "함평군": 46262,
          "완도군": 46192,
          "강진군": 46182,
          "구례군": 46132,
          "영광군": 46252,
          "신안군": 46222,
          "여수시": 46041
        },
        "city_name": "전남",
        "city_code": 46
      },
      {
        "town_list": [
          {
            "ORDERNAME": "47010",
            "CODE": 4701,
            "NAME": "대구시중구"
          },
          {
            "ORDERNAME": "47020",
            "CODE": 4702,
            "NAME": "대구시동구"
          },
          {
            "ORDERNAME": "47030",
            "CODE": 4703,
            "NAME": "대구시남구"
          },
          {
            "ORDERNAME": "47040",
            "CODE": 4704,
            "NAME": "대구시서구"
          },
          {
            "ORDERNAME": "47050",
            "CODE": 4705,
            "NAME": "대구시북구"
          },
          {
            "ORDERNAME": "47061",
            "CODE": 47061,
            "NAME": "포항시"
          },
          {
            "ORDERNAME": "47072",
            "CODE": 47072,
            "NAME": "울릉군"
          },
          {
            "ORDERNAME": "47082",
            "CODE": 47082,
            "NAME": "영일군"
          },
          {
            "ORDERNAME": "47091",
            "CODE": 47091,
            "NAME": "김천시"
          },
          {
            "ORDERNAME": "47102",
            "CODE": 47102,
            "NAME": "금릉군"
          },
          {
            "ORDERNAME": "47111",
            "CODE": 47111,
            "NAME": "경주시"
          },
          {
            "ORDERNAME": "47122",
            "CODE": 47122,
            "NAME": "월성군"
          },
          {
            "ORDERNAME": "47132",
            "CODE": 47132,
            "NAME": "달성군"
          },
          {
            "ORDERNAME": "47142",
            "CODE": 47142,
            "NAME": "고령군"
          },
          {
            "ORDERNAME": "47152",
            "CODE": 47152,
            "NAME": "선산군"
          },
          {
            "ORDERNAME": "47162",
            "CODE": 47162,
            "NAME": "군위군"
          },
          {
            "ORDERNAME": "47172",
            "CODE": 47172,
            "NAME": "의성군"
          },
          {
            "ORDERNAME": "47181",
            "CODE": 47181,
            "NAME": "안동시"
          },
          {
            "ORDERNAME": "47192",
            "CODE": 47192,
            "NAME": "안동군"
          },
          {
            "ORDERNAME": "47202",
            "CODE": 47202,
            "NAME": "영덕군"
          },
          {
            "ORDERNAME": "47212",
            "CODE": 47212,
            "NAME": "청송군"
          },
          {
            "ORDERNAME": "47222",
            "CODE": 47222,
            "NAME": "울진군"
          },
          {
            "ORDERNAME": "47232",
            "CODE": 47232,
            "NAME": "영양군"
          },
          {
            "ORDERNAME": "47242",
            "CODE": 47242,
            "NAME": "영천군"
          },
          {
            "ORDERNAME": "47252",
            "CODE": 47252,
            "NAME": "경산군"
          },
          {
            "ORDERNAME": "47262",
            "CODE": 47262,
            "NAME": "청도군"
          },
          {
            "ORDERNAME": "47272",
            "CODE": 47272,
            "NAME": "성주군"
          },
          {
            "ORDERNAME": "47282",
            "CODE": 47282,
            "NAME": "칠곡군"
          },
          {
            "ORDERNAME": "47292",
            "CODE": 47292,
            "NAME": "상주군"
          },
          {
            "ORDERNAME": "47302",
            "CODE": 47302,
            "NAME": "문경군"
          },
          {
            "ORDERNAME": "47312",
            "CODE": 47312,
            "NAME": "예천군"
          },
          {
            "ORDERNAME": "47322",
            "CODE": 47322,
            "NAME": "영주군"
          },
          {
            "ORDERNAME": "47332",
            "CODE": 47332,
            "NAME": "봉화군"
          }
        ],
        "town_dict": {
          "대구시동구": 4702,
          "영일군": 47082,
          "대구시서구": 4704,
          "경산군": 47252,
          "봉화군": 47332,
          "예천군": 47312,
          "성주군": 47272,
          "군위군": 47162,
          "고령군": 47142,
          "청도군": 47262,
          "울릉군": 47072,
          "문경군": 47302,
          "의성군": 47172,
          "청송군": 47212,
          "금릉군": 47102,
          "울진군": 47222,
          "칠곡군": 47282,
          "달성군": 47132,
          "대구시남구": 4703,
          "영덕군": 47202,
          "월성군": 47122,
          "안동시": 47181,
          "선산군": 47152,
          "김천시": 47091,
          "상주군": 47292,
          "포항시": 47061,
          "대구시북구": 4705,
          "영천군": 47242,
          "안동군": 47192,
          "영양군": 47232,
          "영주군": 47322,
          "대구시중구": 4701,
          "경주시": 47111
        },
        "city_name": "경북",
        "city_code": 47
      },
      {
        "town_list": [
          {
            "ORDERNAME": "48011",
            "CODE": 48011,
            "NAME": "마산시"
          },
          {
            "ORDERNAME": "48021",
            "CODE": 48021,
            "NAME": "진주시"
          },
          {
            "ORDERNAME": "48032",
            "CODE": 48032,
            "NAME": "진양군"
          },
          {
            "ORDERNAME": "48041",
            "CODE": 48041,
            "NAME": "충무시"
          },
          {
            "ORDERNAME": "48052",
            "CODE": 48052,
            "NAME": "통영군"
          },
          {
            "ORDERNAME": "48062",
            "CODE": 48062,
            "NAME": "고성군"
          },
          {
            "ORDERNAME": "48072",
            "CODE": 48072,
            "NAME": "거제군"
          },
          {
            "ORDERNAME": "48091",
            "CODE": 48091,
            "NAME": "진해시"
          },
          {
            "ORDERNAME": "48102",
            "CODE": 48102,
            "NAME": "창원군"
          },
          {
            "ORDERNAME": "48112",
            "CODE": 48112,
            "NAME": "사천군"
          },
          {
            "ORDERNAME": "48121",
            "CODE": 48121,
            "NAME": "삼천포시"
          },
          {
            "ORDERNAME": "48132",
            "CODE": 48132,
            "NAME": "하동군"
          },
          {
            "ORDERNAME": "48142",
            "CODE": 48142,
            "NAME": "함안군"
          },
          {
            "ORDERNAME": "48152",
            "CODE": 48152,
            "NAME": "의령군"
          },
          {
            "ORDERNAME": "48162",
            "CODE": 48162,
            "NAME": "창녕군"
          },
          {
            "ORDERNAME": "48172",
            "CODE": 48172,
            "NAME": "산청군"
          },
          {
            "ORDERNAME": "48182",
            "CODE": 48182,
            "NAME": "합천군"
          },
          {
            "ORDERNAME": "48192",
            "CODE": 48192,
            "NAME": "밀양군"
          },
          {
            "ORDERNAME": "48202",
            "CODE": 48202,
            "NAME": "양산군"
          },
          {
            "ORDERNAME": "48212",
            "CODE": 48212,
            "NAME": "동래군"
          },
          {
            "ORDERNAME": "48221",
            "CODE": 48221,
            "NAME": "울산시"
          },
          {
            "ORDERNAME": "48232",
            "CODE": 48232,
            "NAME": "울주군"
          },
          {
            "ORDERNAME": "48242",
            "CODE": 48242,
            "NAME": "김해군"
          },
          {
            "ORDERNAME": "48252",
            "CODE": 48252,
            "NAME": "남해군"
          },
          {
            "ORDERNAME": "48262",
            "CODE": 48262,
            "NAME": "거창군"
          },
          {
            "ORDERNAME": "48272",
            "CODE": 48272,
            "NAME": "함양군"
          }
        ],
        "town_dict": {
          "함안군": 48142,
          "충무시": 48041,
          "양산군": 48202,
          "울주군": 48232,
          "함양군": 48272,
          "거제군": 48072,
          "진양군": 48032,
          "마산시": 48011,
          "거창군": 48262,
          "고성군": 48062,
          "밀양군": 48192,
          "삼천포시": 48121,
          "사천군": 48112,
          "진주시": 48021,
          "하동군": 48132,
          "남해군": 48252,
          "합천군": 48182,
          "창녕군": 48162,
          "의령군": 48152,
          "김해군": 48242,
          "울산시": 48221,
          "통영군": 48052,
          "진해시": 48091,
          "창원군": 48102,
          "산청군": 48172,
          "동래군": 48212
        },
        "city_name": "경남",
        "city_code": 48
      },
      {
        "town_list": [
          {
            "ORDERNAME": "49011",
            "CODE": 49011,
            "NAME": "제주시"
          },
          {
            "ORDERNAME": "49022",
            "CODE": 49022,
            "NAME": "북제주군"
          },
          {
            "ORDERNAME": "49032",
            "CODE": 49032,
            "NAME": "남제주군"
          }
        ],
        "town_dict": {
          "남제주군": 49032,
          "제주시": 49011,
          "북제주군": 49022
        },
        "city_name": "제주",
        "city_code": 49
      }
    ],
    "election_type": "president",
    "nth": 7
  }
]