[
  {
    "results": [
      {
        "consti_list": [
          {
            "NAME": "서울",
            "CODE": 31100000
          }
        ],
        "town_dict_ORDERNAME": {
          "도봉구갑": 11163,
          "성동구갑": 11043,
          "강동구갑": 11463,
          "동대문구갑": 11083,
          "은평구갑": 11203,
          "송파구갑": 11433,
          "강남구을": 11420,
          "광진구갑": 11063,
          "서초구을": 11400,
          "동작구갑": 11353,
          "중랑구을": 11110,
          "강북구갑": 11143,
          "송파구을": 11440,
          "도봉구을": 11170,
          "광진구을": 11070,
          "동대문구을": 11090,
          "성북구갑": 11123,
          "송파구병": 11450,
          "관악구을": 11380,
          "용산구": 11033,
          "마포구갑": 11243,
          "서대문구갑": 11223,
          "양천구갑": 11263,
          "영등포구갑": 11333,
          "서대문구을": 11230,
          "서초구갑": 11393,
          "영등포구을": 11340,
          "중랑구갑": 11103,
          "강북구을": 11150,
          "성북구을": 11130,
          "노원구갑": 11183,
          "종로구": 11013,
          "금천구": 11323,
          "관악구갑": 11373,
          "성동구을": 11050,
          "양천구을": 11270,
          "동작구을": 11360,
          "은평구을": 11210,
          "강남구갑": 11413,
          "강서구갑": 11283,
          "마포구을": 11250,
          "강동구을": 11470,
          "구로구을": 11310,
          "노원구을": 11190,
          "강서구을": 11290,
          "중구(서울)": 11023,
          "구로구갑": 11303
        },
        "town_dict": {
          "도봉구갑": 11163,
          "성동구갑": 11043,
          "강동구갑": 11463,
          "동대문구갑": 11083,
          "은평구갑": 11203,
          "송파구갑": 11433,
          "강남구을": 11420,
          "광진구갑": 11063,
          "서초구을": 11400,
          "동작구갑": 11353,
          "중랑구을": 1111,
          "강북구갑": 11143,
          "송파구을": 11440,
          "도봉구을": 1117,
          "광진구을": 1107,
          "동대문구을": 1109,
          "성북구갑": 11123,
          "송파구병": 11450,
          "관악구을": 11380,
          "용산구": 11033,
          "마포구갑": 11243,
          "서대문구갑": 11223,
          "양천구갑": 11263,
          "영등포구갑": 11333,
          "서대문구을": 1123,
          "서초구갑": 11393,
          "영등포구을": 11340,
          "중랑구갑": 11103,
          "강북구을": 1115,
          "성북구을": 1113,
          "노원구갑": 11183,
          "종로구": 11013,
          "금천구": 11323,
          "관악구갑": 11373,
          "성동구을": 1105,
          "양천구을": 11270,
          "동작구을": 11360,
          "은평구을": 1121,
          "강남구갑": 11413,
          "강서구갑": 11283,
          "마포구을": 1125,
          "강동구을": 11470,
          "구로구을": 11310,
          "노원구을": 1119,
          "강서구을": 11290,
          "중구(서울)": 11023,
          "구로구갑": 11303
        },
        "consti_dict": {
          "서울": [
            31100000
          ]
        },
        "city_code": 11,
        "city_name": "서울",
        "town_list": [
          {
            "NAME": "종로구",
            "CODE": 11013,
            "ORDERNAME": "11013"
          },
          {
            "NAME": "중구(서울)",
            "CODE": 11023,
            "ORDERNAME": "11023"
          },
          {
            "NAME": "용산구",
            "CODE": 11033,
            "ORDERNAME": "11033"
          },
          {
            "NAME": "성동구갑",
            "CODE": 11043,
            "ORDERNAME": "11043"
          },
          {
            "NAME": "성동구을",
            "CODE": 1105,
            "ORDERNAME": "11050"
          },
          {
            "NAME": "광진구갑",
            "CODE": 11063,
            "ORDERNAME": "11063"
          },
          {
            "NAME": "광진구을",
            "CODE": 1107,
            "ORDERNAME": "11070"
          },
          {
            "NAME": "동대문구갑",
            "CODE": 11083,
            "ORDERNAME": "11083"
          },
          {
            "NAME": "동대문구을",
            "CODE": 1109,
            "ORDERNAME": "11090"
          },
          {
            "NAME": "중랑구갑",
            "CODE": 11103,
            "ORDERNAME": "11103"
          },
          {
            "NAME": "중랑구을",
            "CODE": 1111,
            "ORDERNAME": "11110"
          },
          {
            "NAME": "성북구갑",
            "CODE": 11123,
            "ORDERNAME": "11123"
          },
          {
            "NAME": "성북구을",
            "CODE": 1113,
            "ORDERNAME": "11130"
          },
          {
            "NAME": "강북구갑",
            "CODE": 11143,
            "ORDERNAME": "11143"
          },
          {
            "NAME": "강북구을",
            "CODE": 1115,
            "ORDERNAME": "11150"
          },
          {
            "NAME": "도봉구갑",
            "CODE": 11163,
            "ORDERNAME": "11163"
          },
          {
            "NAME": "도봉구을",
            "CODE": 1117,
            "ORDERNAME": "11170"
          },
          {
            "NAME": "노원구갑",
            "CODE": 11183,
            "ORDERNAME": "11183"
          },
          {
            "NAME": "노원구을",
            "CODE": 1119,
            "ORDERNAME": "11190"
          },
          {
            "NAME": "은평구갑",
            "CODE": 11203,
            "ORDERNAME": "11203"
          },
          {
            "NAME": "은평구을",
            "CODE": 1121,
            "ORDERNAME": "11210"
          },
          {
            "NAME": "서대문구갑",
            "CODE": 11223,
            "ORDERNAME": "11223"
          },
          {
            "NAME": "서대문구을",
            "CODE": 1123,
            "ORDERNAME": "11230"
          },
          {
            "NAME": "마포구갑",
            "CODE": 11243,
            "ORDERNAME": "11243"
          },
          {
            "NAME": "마포구을",
            "CODE": 1125,
            "ORDERNAME": "11250"
          },
          {
            "NAME": "양천구갑",
            "CODE": 11263,
            "ORDERNAME": "11263"
          },
          {
            "NAME": "양천구을",
            "CODE": 11270,
            "ORDERNAME": "11270"
          },
          {
            "NAME": "강서구갑",
            "CODE": 11283,
            "ORDERNAME": "11283"
          },
          {
            "NAME": "강서구을",
            "CODE": 11290,
            "ORDERNAME": "11290"
          },
          {
            "NAME": "구로구갑",
            "CODE": 11303,
            "ORDERNAME": "11303"
          },
          {
            "NAME": "구로구을",
            "CODE": 11310,
            "ORDERNAME": "11310"
          },
          {
            "NAME": "금천구",
            "CODE": 11323,
            "ORDERNAME": "11323"
          },
          {
            "NAME": "영등포구갑",
            "CODE": 11333,
            "ORDERNAME": "11333"
          },
          {
            "NAME": "영등포구을",
            "CODE": 11340,
            "ORDERNAME": "11340"
          },
          {
            "NAME": "동작구갑",
            "CODE": 11353,
            "ORDERNAME": "11353"
          },
          {
            "NAME": "동작구을",
            "CODE": 11360,
            "ORDERNAME": "11360"
          },
          {
            "NAME": "관악구갑",
            "CODE": 11373,
            "ORDERNAME": "11373"
          },
          {
            "NAME": "관악구을",
            "CODE": 11380,
            "ORDERNAME": "11380"
          },
          {
            "NAME": "서초구갑",
            "CODE": 11393,
            "ORDERNAME": "11393"
          },
          {
            "NAME": "서초구을",
            "CODE": 11400,
            "ORDERNAME": "11400"
          },
          {
            "NAME": "강남구갑",
            "CODE": 11413,
            "ORDERNAME": "11413"
          },
          {
            "NAME": "강남구을",
            "CODE": 11420,
            "ORDERNAME": "11420"
          },
          {
            "NAME": "송파구갑",
            "CODE": 11433,
            "ORDERNAME": "11433"
          },
          {
            "NAME": "송파구을",
            "CODE": 11440,
            "ORDERNAME": "11440"
          },
          {
            "NAME": "송파구병",
            "CODE": 11450,
            "ORDERNAME": "11450"
          },
          {
            "NAME": "강동구갑",
            "CODE": 11463,
            "ORDERNAME": "11463"
          },
          {
            "NAME": "강동구을",
            "CODE": 11470,
            "ORDERNAME": "11470"
          }
        ]
      },
      {
        "consti_list": [
          {
            "NAME": "부산",
            "CODE": 32600000
          }
        ],
        "town_dict_ORDERNAME": {
          "금정구갑": 26163,
          "금정구을": 26170,
          "부산진구을": 26060,
          "해운대구": 26123,
          "동래구을": 26080,
          "동구(부산)": 26033,
          "사하구갑": 26143,
          "영도구": 26043,
          "수영구": 26203,
          "기장군": 26135,
          "사상구을": 26220,
          "강서구(부산)": 26183,
          "사하구을": 26150,
          "부산진구갑": 26053,
          "남구을(부산)": 26100,
          "사상구갑": 26213,
          "동래구갑": 26073,
          "서구(부산)": 26023,
          "중구(부산)": 26013,
          "남구갑(부산)": 26093,
          "연제구": 26193,
          "북구(부산)": 26113
        },
        "town_dict": {
          "금정구갑": 26163,
          "금정구을": 26170,
          "부산진구을": 2606,
          "해운대구": 26123,
          "동래구을": 2608,
          "동구(부산)": 26033,
          "사하구갑": 26143,
          "영도구": 26043,
          "수영구": 26203,
          "기장군": 26135,
          "사상구을": 26220,
          "강서구(부산)": 26183,
          "사하구을": 2615,
          "부산진구갑": 26053,
          "남구을(부산)": 2610,
          "사상구갑": 26213,
          "동래구갑": 26073,
          "서구(부산)": 26023,
          "중구(부산)": 26013,
          "남구갑(부산)": 26093,
          "연제구": 26193,
          "북구(부산)": 26113
        },
        "consti_dict": {
          "부산": [
            32600000
          ]
        },
        "city_code": 26,
        "city_name": "부산",
        "town_list": [
          {
            "NAME": "중구(부산)",
            "CODE": 26013,
            "ORDERNAME": "26013"
          },
          {
            "NAME": "서구(부산)",
            "CODE": 26023,
            "ORDERNAME": "26023"
          },
          {
            "NAME": "동구(부산)",
            "CODE": 26033,
            "ORDERNAME": "26033"
          },
          {
            "NAME": "영도구",
            "CODE": 26043,
            "ORDERNAME": "26043"
          },
          {
            "NAME": "부산진구갑",
            "CODE": 26053,
            "ORDERNAME": "26053"
          },
          {
            "NAME": "부산진구을",
            "CODE": 2606,
            "ORDERNAME": "26060"
          },
          {
            "NAME": "동래구갑",
            "CODE": 26073,
            "ORDERNAME": "26073"
          },
          {
            "NAME": "동래구을",
            "CODE": 2608,
            "ORDERNAME": "26080"
          },
          {
            "NAME": "남구갑(부산)",
            "CODE": 26093,
            "ORDERNAME": "26093"
          },
          {
            "NAME": "남구을(부산)",
            "CODE": 2610,
            "ORDERNAME": "26100"
          },
          {
            "NAME": "북구(부산)",
            "CODE": 26113,
            "ORDERNAME": "26113"
          },
          {
            "NAME": "해운대구",
            "CODE": 26123,
            "ORDERNAME": "26123"
          },
          {
            "NAME": "기장군",
            "CODE": 26135,
            "ORDERNAME": "26135"
          },
          {
            "NAME": "사하구갑",
            "CODE": 26143,
            "ORDERNAME": "26143"
          },
          {
            "NAME": "사하구을",
            "CODE": 2615,
            "ORDERNAME": "26150"
          },
          {
            "NAME": "금정구갑",
            "CODE": 26163,
            "ORDERNAME": "26163"
          },
          {
            "NAME": "금정구을",
            "CODE": 26170,
            "ORDERNAME": "26170"
          },
          {
            "NAME": "강서구(부산)",
            "CODE": 26183,
            "ORDERNAME": "26183"
          },
          {
            "NAME": "연제구",
            "CODE": 26193,
            "ORDERNAME": "26193"
          },
          {
            "NAME": "수영구",
            "CODE": 26203,
            "ORDERNAME": "26203"
          },
          {
            "NAME": "사상구갑",
            "CODE": 26213,
            "ORDERNAME": "26213"
          },
          {
            "NAME": "사상구을",
            "CODE": 26220,
            "ORDERNAME": "26220"
          }
        ]
      },
      {
        "consti_list": [
          {
            "NAME": "대구",
            "CODE": 32700000
          }
        ],
        "town_dict_ORDERNAME": {
          "달서구갑": 27113,
          "남구(대구)": 27063,
          "달서구을": 27120,
          "북구을(대구)": 27080,
          "서구을(대구)": 27050,
          "수성구갑": 27093,
          "중구(대구)": 27013,
          "동구갑(대구)": 27023,
          "수성구을": 27100,
          "서구갑(대구)": 27043,
          "달성군": 27135,
          "동구을(대구)": 27030,
          "북구갑(대구)": 27073
        },
        "town_dict": {
          "달서구갑": 27113,
          "남구(대구)": 27063,
          "달서구을": 27120,
          "북구을(대구)": 2708,
          "서구을(대구)": 2705,
          "수성구갑": 27093,
          "중구(대구)": 27013,
          "동구갑(대구)": 27023,
          "수성구을": 27100,
          "서구갑(대구)": 27043,
          "달성군": 27135,
          "동구을(대구)": 2703,
          "북구갑(대구)": 27073
        },
        "consti_dict": {
          "대구": [
            32700000
          ]
        },
        "city_code": 27,
        "city_name": "대구",
        "town_list": [
          {
            "NAME": "중구(대구)",
            "CODE": 27013,
            "ORDERNAME": "27013"
          },
          {
            "NAME": "동구갑(대구)",
            "CODE": 27023,
            "ORDERNAME": "27023"
          },
          {
            "NAME": "동구을(대구)",
            "CODE": 2703,
            "ORDERNAME": "27030"
          },
          {
            "NAME": "서구갑(대구)",
            "CODE": 27043,
            "ORDERNAME": "27043"
          },
          {
            "NAME": "서구을(대구)",
            "CODE": 2705,
            "ORDERNAME": "27050"
          },
          {
            "NAME": "남구(대구)",
            "CODE": 27063,
            "ORDERNAME": "27063"
          },
          {
            "NAME": "북구갑(대구)",
            "CODE": 27073,
            "ORDERNAME": "27073"
          },
          {
            "NAME": "북구을(대구)",
            "CODE": 2708,
            "ORDERNAME": "27080"
          },
          {
            "NAME": "수성구갑",
            "CODE": 27093,
            "ORDERNAME": "27093"
          },
          {
            "NAME": "수성구을",
            "CODE": 27100,
            "ORDERNAME": "27100"
          },
          {
            "NAME": "달서구갑",
            "CODE": 27113,
            "ORDERNAME": "27113"
          },
          {
            "NAME": "달서구을",
            "CODE": 27120,
            "ORDERNAME": "27120"
          },
          {
            "NAME": "달성군",
            "CODE": 27135,
            "ORDERNAME": "27135"
          }
        ]
      },
      {
        "consti_list": [
          {
            "NAME": "인천",
            "CODE": 32800000
          }
        ],
        "town_dict_ORDERNAME": {
          "강화군": 28125,
          "연수구": 28053,
          "동구(인천)": 28023,
          "계양구": 28103,
          "남구갑(인천)": 28033,
          "부평구갑": 28083,
          "부평구을": 28090,
          "옹진군": 28135,
          "서구(인천)": 28113,
          "남구을(인천)": 28040,
          "남동구갑": 28063,
          "중구(인천)": 28013,
          "남동구을": 28070
        },
        "town_dict": {
          "강화군": 28125,
          "연수구": 28053,
          "동구(인천)": 28023,
          "계양구": 28103,
          "남구갑(인천)": 28033,
          "부평구갑": 28083,
          "부평구을": 2809,
          "옹진군": 28135,
          "서구(인천)": 28113,
          "남구을(인천)": 2804,
          "남동구갑": 28063,
          "중구(인천)": 28013,
          "남동구을": 2807
        },
        "consti_dict": {
          "인천": [
            32800000
          ]
        },
        "city_code": 28,
        "city_name": "인천",
        "town_list": [
          {
            "NAME": "중구(인천)",
            "CODE": 28013,
            "ORDERNAME": "28013"
          },
          {
            "NAME": "동구(인천)",
            "CODE": 28023,
            "ORDERNAME": "28023"
          },
          {
            "NAME": "남구갑(인천)",
            "CODE": 28033,
            "ORDERNAME": "28033"
          },
          {
            "NAME": "남구을(인천)",
            "CODE": 2804,
            "ORDERNAME": "28040"
          },
          {
            "NAME": "연수구",
            "CODE": 28053,
            "ORDERNAME": "28053"
          },
          {
            "NAME": "남동구갑",
            "CODE": 28063,
            "ORDERNAME": "28063"
          },
          {
            "NAME": "남동구을",
            "CODE": 2807,
            "ORDERNAME": "28070"
          },
          {
            "NAME": "부평구갑",
            "CODE": 28083,
            "ORDERNAME": "28083"
          },
          {
            "NAME": "부평구을",
            "CODE": 2809,
            "ORDERNAME": "28090"
          },
          {
            "NAME": "계양구",
            "CODE": 28103,
            "ORDERNAME": "28103"
          },
          {
            "NAME": "서구(인천)",
            "CODE": 28113,
            "ORDERNAME": "28113"
          },
          {
            "NAME": "강화군",
            "CODE": 28125,
            "ORDERNAME": "28125"
          },
          {
            "NAME": "옹진군",
            "CODE": 28135,
            "ORDERNAME": "28135"
          }
        ]
      },
      {
        "consti_list": [
          {
            "NAME": "광주",
            "CODE": 32900000
          }
        ],
        "town_dict_ORDERNAME": {
          "남구(광주)": 29033,
          "서구(광주)": 29023,
          "동구(광주)": 29013,
          "광산구": 29063,
          "북구갑(광주)": 29043,
          "북구을(광주)": 29050
        },
        "town_dict": {
          "남구(광주)": 29033,
          "서구(광주)": 29023,
          "동구(광주)": 29013,
          "광산구": 29063,
          "북구갑(광주)": 29043,
          "북구을(광주)": 29050
        },
        "consti_dict": {
          "광주": [
            32900000
          ]
        },
        "city_code": 29,
        "city_name": "광주",
        "town_list": [
          {
            "NAME": "동구(광주)",
            "CODE": 29013,
            "ORDERNAME": "29013"
          },
          {
            "NAME": "서구(광주)",
            "CODE": 29023,
            "ORDERNAME": "29023"
          },
          {
            "NAME": "남구(광주)",
            "CODE": 29033,
            "ORDERNAME": "29033"
          },
          {
            "NAME": "북구갑(광주)",
            "CODE": 29043,
            "ORDERNAME": "29043"
          },
          {
            "NAME": "북구을(광주)",
            "CODE": 29050,
            "ORDERNAME": "29050"
          },
          {
            "NAME": "광산구",
            "CODE": 29063,
            "ORDERNAME": "29063"
          }
        ]
      },
      {
        "consti_list": [
          {
            "NAME": "대전",
            "CODE": 33000000
          }
        ],
        "town_dict_ORDERNAME": {
          "중구(대전)": 30033,
          "서구갑(대전)": 30043,
          "서구을(대전)": 30050,
          "대덕구": 30073,
          "동구갑(대전)": 30013,
          "유성구": 30063,
          "동구을(대전)": 30020
        },
        "town_dict": {
          "중구(대전)": 30033,
          "서구갑(대전)": 30043,
          "서구을(대전)": 3005,
          "대덕구": 30073,
          "동구갑(대전)": 30013,
          "유성구": 30063,
          "동구을(대전)": 3002
        },
        "consti_dict": {
          "대전": [
            33000000
          ]
        },
        "city_code": 30,
        "city_name": "대전",
        "town_list": [
          {
            "NAME": "동구갑(대전)",
            "CODE": 30013,
            "ORDERNAME": "30013"
          },
          {
            "NAME": "동구을(대전)",
            "CODE": 3002,
            "ORDERNAME": "30020"
          },
          {
            "NAME": "중구(대전)",
            "CODE": 30033,
            "ORDERNAME": "30033"
          },
          {
            "NAME": "서구갑(대전)",
            "CODE": 30043,
            "ORDERNAME": "30043"
          },
          {
            "NAME": "서구을(대전)",
            "CODE": 3005,
            "ORDERNAME": "30050"
          },
          {
            "NAME": "유성구",
            "CODE": 30063,
            "ORDERNAME": "30063"
          },
          {
            "NAME": "대덕구",
            "CODE": 30073,
            "ORDERNAME": "30073"
          }
        ]
      },
      {
        "consti_list": [
          {
            "NAME": "울산",
            "CODE": 33100000
          }
        ],
        "town_dict_ORDERNAME": {
          "남구갑(울산)": 31023,
          "남구을(울산)": 31030,
          "동구(울산)": 31043,
          "중구(울산)": 31013,
          "울주군": 31065,
          "북구(울산)": 31053
        },
        "town_dict": {
          "남구갑(울산)": 31023,
          "남구을(울산)": 3103,
          "동구(울산)": 31043,
          "중구(울산)": 31013,
          "울주군": 31065,
          "북구(울산)": 31053
        },
        "consti_dict": {
          "울산": [
            33100000
          ]
        },
        "city_code": 31,
        "city_name": "울산",
        "town_list": [
          {
            "NAME": "중구(울산)",
            "CODE": 31013,
            "ORDERNAME": "31013"
          },
          {
            "NAME": "남구갑(울산)",
            "CODE": 31023,
            "ORDERNAME": "31023"
          },
          {
            "NAME": "남구을(울산)",
            "CODE": 3103,
            "ORDERNAME": "31030"
          },
          {
            "NAME": "동구(울산)",
            "CODE": 31043,
            "ORDERNAME": "31043"
          },
          {
            "NAME": "북구(울산)",
            "CODE": 31053,
            "ORDERNAME": "31053"
          },
          {
            "NAME": "울주군",
            "CODE": 31065,
            "ORDERNAME": "31065"
          }
        ]
      },
      {
        "consti_list": [
          {
            "NAME": "경기",
            "CODE": 34100000
          }
        ],
        "town_dict_ORDERNAME": {
          "용인시": 41424,
          "과천시": 41254,
          "안양시만안구": 41080,
          "남양주시": 41284,
          "양평군": 41395,
          "고양시덕양구": 41233,
          "시흥시": 41314,
          "평택시을": 41181,
          "연천군": 41385,
          "안성시": 41434,
          "파주시": 41364,
          "고양시일산구": 41240,
          "안산시갑": 41214,
          "양주군": 41205,
          "부천시원미구갑": 41113,
          "동두천시": 41194,
          "수원시권선구": 41020,
          "의왕시": 41264,
          "성남시중원구": 41050,
          "의정부시": 41074,
          "부천시원미구을": 41120,
          "안양시동안구을": 41100,
          "여주군": 41355,
          "성남시수정구": 41043,
          "수원시팔달구": 41033,
          "화성군": 41305,
          "하남시": 41334,
          "광주군": 41345,
          "김포시": 41444,
          "안양시동안구갑": 41093,
          "구리시": 41274,
          "광명시을": 41161,
          "광명시갑": 41154,
          "이천시": 41414,
          "부천시오정구": 41140,
          "수원시장안구": 41010,
          "포천군": 41375,
          "부천시소사구": 41130,
          "오산시": 41294,
          "평택시갑": 41174,
          "안산시을": 41221,
          "성남시분당구": 41060,
          "가평군": 41405,
          "군포시": 41324
        },
        "town_dict": {
          "용인시": 41424,
          "과천시": 41254,
          "안양시만안구": 4108,
          "남양주시": 41284,
          "양평군": 41395,
          "고양시덕양구": 41233,
          "시흥시": 41314,
          "평택시을": 41181,
          "연천군": 41385,
          "안성시": 41434,
          "파주시": 41364,
          "고양시일산구": 4124,
          "안산시갑": 41214,
          "양주군": 41205,
          "부천시원미구갑": 41113,
          "동두천시": 41194,
          "수원시권선구": 4102,
          "의왕시": 41264,
          "성남시중원구": 4105,
          "의정부시": 41074,
          "부천시원미구을": 4112,
          "안양시동안구을": 4110,
          "여주군": 41355,
          "성남시수정구": 41043,
          "수원시팔달구": 41033,
          "화성군": 41305,
          "하남시": 41334,
          "광주군": 41345,
          "김포시": 41444,
          "안양시동안구갑": 41093,
          "구리시": 41274,
          "광명시을": 41161,
          "광명시갑": 41154,
          "이천시": 41414,
          "부천시오정구": 4114,
          "수원시장안구": 4101,
          "포천군": 41375,
          "부천시소사구": 4113,
          "오산시": 41294,
          "평택시갑": 41174,
          "안산시을": 41221,
          "성남시분당구": 4106,
          "가평군": 41405,
          "군포시": 41324
        },
        "consti_dict": {
          "경기": [
            34100000
          ]
        },
        "city_code": 41,
        "city_name": "경기",
        "town_list": [
          {
            "NAME": "수원시장안구",
            "CODE": 4101,
            "ORDERNAME": "41010"
          },
          {
            "NAME": "수원시권선구",
            "CODE": 4102,
            "ORDERNAME": "41020"
          },
          {
            "NAME": "수원시팔달구",
            "CODE": 41033,
            "ORDERNAME": "41033"
          },
          {
            "NAME": "성남시수정구",
            "CODE": 41043,
            "ORDERNAME": "41043"
          },
          {
            "NAME": "성남시중원구",
            "CODE": 4105,
            "ORDERNAME": "41050"
          },
          {
            "NAME": "성남시분당구",
            "CODE": 4106,
            "ORDERNAME": "41060"
          },
          {
            "NAME": "의정부시",
            "CODE": 41074,
            "ORDERNAME": "41074"
          },
          {
            "NAME": "안양시만안구",
            "CODE": 4108,
            "ORDERNAME": "41080"
          },
          {
            "NAME": "안양시동안구갑",
            "CODE": 41093,
            "ORDERNAME": "41093"
          },
          {
            "NAME": "안양시동안구을",
            "CODE": 4110,
            "ORDERNAME": "41100"
          },
          {
            "NAME": "부천시원미구갑",
            "CODE": 41113,
            "ORDERNAME": "41113"
          },
          {
            "NAME": "부천시원미구을",
            "CODE": 4112,
            "ORDERNAME": "41120"
          },
          {
            "NAME": "부천시소사구",
            "CODE": 4113,
            "ORDERNAME": "41130"
          },
          {
            "NAME": "부천시오정구",
            "CODE": 4114,
            "ORDERNAME": "41140"
          },
          {
            "NAME": "광명시갑",
            "CODE": 41154,
            "ORDERNAME": "41154"
          },
          {
            "NAME": "광명시을",
            "CODE": 41161,
            "ORDERNAME": "41161"
          },
          {
            "NAME": "평택시갑",
            "CODE": 41174,
            "ORDERNAME": "41174"
          },
          {
            "NAME": "평택시을",
            "CODE": 41181,
            "ORDERNAME": "41181"
          },
          {
            "NAME": "동두천시",
            "CODE": 41194,
            "ORDERNAME": "41194"
          },
          {
            "NAME": "양주군",
            "CODE": 41205,
            "ORDERNAME": "41205"
          },
          {
            "NAME": "안산시갑",
            "CODE": 41214,
            "ORDERNAME": "41214"
          },
          {
            "NAME": "안산시을",
            "CODE": 41221,
            "ORDERNAME": "41221"
          },
          {
            "NAME": "고양시덕양구",
            "CODE": 41233,
            "ORDERNAME": "41233"
          },
          {
            "NAME": "고양시일산구",
            "CODE": 4124,
            "ORDERNAME": "41240"
          },
          {
            "NAME": "과천시",
            "CODE": 41254,
            "ORDERNAME": "41254"
          },
          {
            "NAME": "의왕시",
            "CODE": 41264,
            "ORDERNAME": "41264"
          },
          {
            "NAME": "구리시",
            "CODE": 41274,
            "ORDERNAME": "41274"
          },
          {
            "NAME": "남양주시",
            "CODE": 41284,
            "ORDERNAME": "41284"
          },
          {
            "NAME": "오산시",
            "CODE": 41294,
            "ORDERNAME": "41294"
          },
          {
            "NAME": "화성군",
            "CODE": 41305,
            "ORDERNAME": "41305"
          },
          {
            "NAME": "시흥시",
            "CODE": 41314,
            "ORDERNAME": "41314"
          },
          {
            "NAME": "군포시",
            "CODE": 41324,
            "ORDERNAME": "41324"
          },
          {
            "NAME": "하남시",
            "CODE": 41334,
            "ORDERNAME": "41334"
          },
          {
            "NAME": "광주군",
            "CODE": 41345,
            "ORDERNAME": "41345"
          },
          {
            "NAME": "여주군",
            "CODE": 41355,
            "ORDERNAME": "41355"
          },
          {
            "NAME": "파주시",
            "CODE": 41364,
            "ORDERNAME": "41364"
          },
          {
            "NAME": "포천군",
            "CODE": 41375,
            "ORDERNAME": "41375"
          },
          {
            "NAME": "연천군",
            "CODE": 41385,
            "ORDERNAME": "41385"
          },
          {
            "NAME": "양평군",
            "CODE": 41395,
            "ORDERNAME": "41395"
          },
          {
            "NAME": "가평군",
            "CODE": 41405,
            "ORDERNAME": "41405"
          },
          {
            "NAME": "이천시",
            "CODE": 41414,
            "ORDERNAME": "41414"
          },
          {
            "NAME": "용인시",
            "CODE": 41424,
            "ORDERNAME": "41424"
          },
          {
            "NAME": "안성시",
            "CODE": 41434,
            "ORDERNAME": "41434"
          },
          {
            "NAME": "김포시",
            "CODE": 41444,
            "ORDERNAME": "41444"
          }
        ]
      },
      {
        "consti_list": [
          {
            "NAME": "강원",
            "CODE": 34200000
          }
        ],
        "town_dict_ORDERNAME": {
          "춘천시을": 42021,
          "원주시을": 42041,
          "양구군": 42215,
          "춘천시갑": 42014,
          "철원군": 42205,
          "삼척시": 42144,
          "태백시": 42084,
          "홍천군": 42155,
          "횡성군": 42165,
          "고성군": 42115,
          "인제군": 42135,
          "강릉시갑": 42054,
          "정선군": 42095,
          "원주시갑": 42034,
          "양양군": 42125,
          "동해시": 42074,
          "평창군": 42185,
          "속초시": 42104,
          "화천군": 42195,
          "강릉시을": 42061,
          "영월군": 42175
        },
        "town_dict": {
          "춘천시을": 42021,
          "원주시을": 42041,
          "양구군": 42215,
          "춘천시갑": 42014,
          "철원군": 42205,
          "삼척시": 42144,
          "태백시": 42084,
          "홍천군": 42155,
          "횡성군": 42165,
          "고성군": 42115,
          "인제군": 42135,
          "강릉시갑": 42054,
          "정선군": 42095,
          "원주시갑": 42034,
          "양양군": 42125,
          "동해시": 42074,
          "평창군": 42185,
          "속초시": 42104,
          "화천군": 42195,
          "강릉시을": 42061,
          "영월군": 42175
        },
        "consti_dict": {
          "강원": [
            34200000
          ]
        },
        "city_code": 42,
        "city_name": "강원",
        "town_list": [
          {
            "NAME": "춘천시갑",
            "CODE": 42014,
            "ORDERNAME": "42014"
          },
          {
            "NAME": "춘천시을",
            "CODE": 42021,
            "ORDERNAME": "42021"
          },
          {
            "NAME": "원주시갑",
            "CODE": 42034,
            "ORDERNAME": "42034"
          },
          {
            "NAME": "원주시을",
            "CODE": 42041,
            "ORDERNAME": "42041"
          },
          {
            "NAME": "강릉시갑",
            "CODE": 42054,
            "ORDERNAME": "42054"
          },
          {
            "NAME": "강릉시을",
            "CODE": 42061,
            "ORDERNAME": "42061"
          },
          {
            "NAME": "동해시",
            "CODE": 42074,
            "ORDERNAME": "42074"
          },
          {
            "NAME": "태백시",
            "CODE": 42084,
            "ORDERNAME": "42084"
          },
          {
            "NAME": "정선군",
            "CODE": 42095,
            "ORDERNAME": "42095"
          },
          {
            "NAME": "속초시",
            "CODE": 42104,
            "ORDERNAME": "42104"
          },
          {
            "NAME": "고성군",
            "CODE": 42115,
            "ORDERNAME": "42115"
          },
          {
            "NAME": "양양군",
            "CODE": 42125,
            "ORDERNAME": "42125"
          },
          {
            "NAME": "인제군",
            "CODE": 42135,
            "ORDERNAME": "42135"
          },
          {
            "NAME": "삼척시",
            "CODE": 42144,
            "ORDERNAME": "42144"
          },
          {
            "NAME": "홍천군",
            "CODE": 42155,
            "ORDERNAME": "42155"
          },
          {
            "NAME": "횡성군",
            "CODE": 42165,
            "ORDERNAME": "42165"
          },
          {
            "NAME": "영월군",
            "CODE": 42175,
            "ORDERNAME": "42175"
          },
          {
            "NAME": "평창군",
            "CODE": 42185,
            "ORDERNAME": "42185"
          },
          {
            "NAME": "화천군",
            "CODE": 42195,
            "ORDERNAME": "42195"
          },
          {
            "NAME": "철원군",
            "CODE": 42205,
            "ORDERNAME": "42205"
          },
          {
            "NAME": "양구군",
            "CODE": 42215,
            "ORDERNAME": "42215"
          }
        ]
      },
      {
        "consti_list": [
          {
            "NAME": "충북",
            "CODE": 34300000
          }
        ],
        "town_dict_ORDERNAME": {
          "충주시": 43034,
          "진천군": 43115,
          "청주시상당구": 43013,
          "제천시": 43044,
          "음성군": 43105,
          "단양군": 43055,
          "영동군": 43075,
          "청주시흥덕구": 43020,
          "청원군": 43065,
          "괴산군": 43125,
          "보은군": 43085,
          "옥천군": 43095
        },
        "town_dict": {
          "충주시": 43034,
          "진천군": 43115,
          "청주시상당구": 43013,
          "제천시": 43044,
          "음성군": 43105,
          "단양군": 43055,
          "영동군": 43075,
          "청주시흥덕구": 4302,
          "청원군": 43065,
          "괴산군": 43125,
          "보은군": 43085,
          "옥천군": 43095
        },
        "consti_dict": {
          "충북": [
            34300000
          ]
        },
        "city_code": 43,
        "city_name": "충북",
        "town_list": [
          {
            "NAME": "청주시상당구",
            "CODE": 43013,
            "ORDERNAME": "43013"
          },
          {
            "NAME": "청주시흥덕구",
            "CODE": 4302,
            "ORDERNAME": "43020"
          },
          {
            "NAME": "충주시",
            "CODE": 43034,
            "ORDERNAME": "43034"
          },
          {
            "NAME": "제천시",
            "CODE": 43044,
            "ORDERNAME": "43044"
          },
          {
            "NAME": "단양군",
            "CODE": 43055,
            "ORDERNAME": "43055"
          },
          {
            "NAME": "청원군",
            "CODE": 43065,
            "ORDERNAME": "43065"
          },
          {
            "NAME": "영동군",
            "CODE": 43075,
            "ORDERNAME": "43075"
          },
          {
            "NAME": "보은군",
            "CODE": 43085,
            "ORDERNAME": "43085"
          },
          {
            "NAME": "옥천군",
            "CODE": 43095,
            "ORDERNAME": "43095"
          },
          {
            "NAME": "음성군",
            "CODE": 43105,
            "ORDERNAME": "43105"
          },
          {
            "NAME": "진천군",
            "CODE": 43115,
            "ORDERNAME": "43115"
          },
          {
            "NAME": "괴산군",
            "CODE": 43125,
            "ORDERNAME": "43125"
          }
        ]
      },
      {
        "consti_list": [
          {
            "NAME": "충남",
            "CODE": 34400000
          }
        ],
        "town_dict_ORDERNAME": {
          "논산시": 44084,
          "예산군": 44135,
          "천안시을": 44021,
          "연기군": 44075,
          "천안시갑": 44014,
          "청양군": 44125,
          "태안군": 44155,
          "공주시": 44034,
          "금산군": 44065,
          "홍성군": 44115,
          "부여군": 44095,
          "당진군": 44165,
          "서천군": 44105,
          "보령시": 44044,
          "서산시": 44144,
          "아산시": 44054
        },
        "town_dict": {
          "논산시": 44084,
          "예산군": 44135,
          "천안시을": 44021,
          "연기군": 44075,
          "천안시갑": 44014,
          "청양군": 44125,
          "태안군": 44155,
          "공주시": 44034,
          "금산군": 44065,
          "홍성군": 44115,
          "부여군": 44095,
          "당진군": 44165,
          "서천군": 44105,
          "보령시": 44044,
          "서산시": 44144,
          "아산시": 44054
        },
        "consti_dict": {
          "충남": [
            34400000
          ]
        },
        "city_code": 44,
        "city_name": "충남",
        "town_list": [
          {
            "NAME": "천안시갑",
            "CODE": 44014,
            "ORDERNAME": "44014"
          },
          {
            "NAME": "천안시을",
            "CODE": 44021,
            "ORDERNAME": "44021"
          },
          {
            "NAME": "공주시",
            "CODE": 44034,
            "ORDERNAME": "44034"
          },
          {
            "NAME": "보령시",
            "CODE": 44044,
            "ORDERNAME": "44044"
          },
          {
            "NAME": "아산시",
            "CODE": 44054,
            "ORDERNAME": "44054"
          },
          {
            "NAME": "금산군",
            "CODE": 44065,
            "ORDERNAME": "44065"
          },
          {
            "NAME": "연기군",
            "CODE": 44075,
            "ORDERNAME": "44075"
          },
          {
            "NAME": "논산시",
            "CODE": 44084,
            "ORDERNAME": "44084"
          },
          {
            "NAME": "부여군",
            "CODE": 44095,
            "ORDERNAME": "44095"
          },
          {
            "NAME": "서천군",
            "CODE": 44105,
            "ORDERNAME": "44105"
          },
          {
            "NAME": "홍성군",
            "CODE": 44115,
            "ORDERNAME": "44115"
          },
          {
            "NAME": "청양군",
            "CODE": 44125,
            "ORDERNAME": "44125"
          },
          {
            "NAME": "예산군",
            "CODE": 44135,
            "ORDERNAME": "44135"
          },
          {
            "NAME": "서산시",
            "CODE": 44144,
            "ORDERNAME": "44144"
          },
          {
            "NAME": "태안군",
            "CODE": 44155,
            "ORDERNAME": "44155"
          },
          {
            "NAME": "당진군",
            "CODE": 44165,
            "ORDERNAME": "44165"
          }
        ]
      },
      {
        "consti_list": [
          {
            "NAME": "전북",
            "CODE": 34500000
          }
        ],
        "town_dict_ORDERNAME": {
          "전주시덕진구": 45023,
          "무주군": 45125,
          "진안군": 45115,
          "군산시갑": 45034,
          "익산시을": 45061,
          "장수군": 45135,
          "김제시": 45094,
          "완주군": 45105,
          "순창군": 45155,
          "전주시완산구": 45010,
          "임실군": 45145,
          "부안군": 45175,
          "남원시": 45084,
          "정읍시": 45074,
          "고창군": 45165,
          "군산시을": 45041,
          "익산시갑": 45054
        },
        "town_dict": {
          "전주시덕진구": 45023,
          "무주군": 45125,
          "진안군": 45115,
          "군산시갑": 45034,
          "익산시을": 45061,
          "장수군": 45135,
          "김제시": 45094,
          "완주군": 45105,
          "순창군": 45155,
          "전주시완산구": 4501,
          "임실군": 45145,
          "부안군": 45175,
          "남원시": 45084,
          "정읍시": 45074,
          "고창군": 45165,
          "군산시을": 45041,
          "익산시갑": 45054
        },
        "consti_dict": {
          "전북": [
            34500000
          ]
        },
        "city_code": 45,
        "city_name": "전북",
        "town_list": [
          {
            "NAME": "전주시완산구",
            "CODE": 4501,
            "ORDERNAME": "45010"
          },
          {
            "NAME": "전주시덕진구",
            "CODE": 45023,
            "ORDERNAME": "45023"
          },
          {
            "NAME": "군산시갑",
            "CODE": 45034,
            "ORDERNAME": "45034"
          },
          {
            "NAME": "군산시을",
            "CODE": 45041,
            "ORDERNAME": "45041"
          },
          {
            "NAME": "익산시갑",
            "CODE": 45054,
            "ORDERNAME": "45054"
          },
          {
            "NAME": "익산시을",
            "CODE": 45061,
            "ORDERNAME": "45061"
          },
          {
            "NAME": "정읍시",
            "CODE": 45074,
            "ORDERNAME": "45074"
          },
          {
            "NAME": "남원시",
            "CODE": 45084,
            "ORDERNAME": "45084"
          },
          {
            "NAME": "김제시",
            "CODE": 45094,
            "ORDERNAME": "45094"
          },
          {
            "NAME": "완주군",
            "CODE": 45105,
            "ORDERNAME": "45105"
          },
          {
            "NAME": "진안군",
            "CODE": 45115,
            "ORDERNAME": "45115"
          },
          {
            "NAME": "무주군",
            "CODE": 45125,
            "ORDERNAME": "45125"
          },
          {
            "NAME": "장수군",
            "CODE": 45135,
            "ORDERNAME": "45135"
          },
          {
            "NAME": "임실군",
            "CODE": 45145,
            "ORDERNAME": "45145"
          },
          {
            "NAME": "순창군",
            "CODE": 45155,
            "ORDERNAME": "45155"
          },
          {
            "NAME": "고창군",
            "CODE": 45165,
            "ORDERNAME": "45165"
          },
          {
            "NAME": "부안군",
            "CODE": 45175,
            "ORDERNAME": "45175"
          }
        ]
      },
      {
        "consti_list": [
          {
            "NAME": "전남",
            "CODE": 34600000
          }
        ],
        "town_dict_ORDERNAME": {
          "보성군": 46135,
          "곡성군": 46105,
          "영광군": 46225,
          "신안군": 46245,
          "강진군": 46165,
          "영암군": 46205,
          "여수시갑": 46024,
          "구례군": 46115,
          "순천시을": 46051,
          "장성군": 46095,
          "장흥군": 46155,
          "해남군": 46185,
          "여수시을": 46031,
          "함평군": 46235,
          "나주시": 46064,
          "고흥군": 46125,
          "진도군": 46195,
          "광양시": 46074,
          "순천시갑": 46044,
          "완도군": 46175,
          "담양군": 46085,
          "목포시": 46014,
          "화순군": 46145,
          "무안군": 46215
        },
        "town_dict": {
          "보성군": 46135,
          "곡성군": 46105,
          "영광군": 46225,
          "신안군": 46245,
          "강진군": 46165,
          "영암군": 46205,
          "여수시갑": 46024,
          "구례군": 46115,
          "순천시을": 46051,
          "장성군": 46095,
          "장흥군": 46155,
          "해남군": 46185,
          "여수시을": 46031,
          "함평군": 46235,
          "나주시": 46064,
          "고흥군": 46125,
          "진도군": 46195,
          "광양시": 46074,
          "순천시갑": 46044,
          "완도군": 46175,
          "담양군": 46085,
          "목포시": 46014,
          "화순군": 46145,
          "무안군": 46215
        },
        "consti_dict": {
          "전남": [
            34600000
          ]
        },
        "city_code": 46,
        "city_name": "전남",
        "town_list": [
          {
            "NAME": "목포시",
            "CODE": 46014,
            "ORDERNAME": "46014"
          },
          {
            "NAME": "여수시갑",
            "CODE": 46024,
            "ORDERNAME": "46024"
          },
          {
            "NAME": "여수시을",
            "CODE": 46031,
            "ORDERNAME": "46031"
          },
          {
            "NAME": "순천시갑",
            "CODE": 46044,
            "ORDERNAME": "46044"
          },
          {
            "NAME": "순천시을",
            "CODE": 46051,
            "ORDERNAME": "46051"
          },
          {
            "NAME": "나주시",
            "CODE": 46064,
            "ORDERNAME": "46064"
          },
          {
            "NAME": "광양시",
            "CODE": 46074,
            "ORDERNAME": "46074"
          },
          {
            "NAME": "담양군",
            "CODE": 46085,
            "ORDERNAME": "46085"
          },
          {
            "NAME": "장성군",
            "CODE": 46095,
            "ORDERNAME": "46095"
          },
          {
            "NAME": "곡성군",
            "CODE": 46105,
            "ORDERNAME": "46105"
          },
          {
            "NAME": "구례군",
            "CODE": 46115,
            "ORDERNAME": "46115"
          },
          {
            "NAME": "고흥군",
            "CODE": 46125,
            "ORDERNAME": "46125"
          },
          {
            "NAME": "보성군",
            "CODE": 46135,
            "ORDERNAME": "46135"
          },
          {
            "NAME": "화순군",
            "CODE": 46145,
            "ORDERNAME": "46145"
          },
          {
            "NAME": "장흥군",
            "CODE": 46155,
            "ORDERNAME": "46155"
          },
          {
            "NAME": "강진군",
            "CODE": 46165,
            "ORDERNAME": "46165"
          },
          {
            "NAME": "완도군",
            "CODE": 46175,
            "ORDERNAME": "46175"
          },
          {
            "NAME": "해남군",
            "CODE": 46185,
            "ORDERNAME": "46185"
          },
          {
            "NAME": "진도군",
            "CODE": 46195,
            "ORDERNAME": "46195"
          },
          {
            "NAME": "영암군",
            "CODE": 46205,
            "ORDERNAME": "46205"
          },
          {
            "NAME": "무안군",
            "CODE": 46215,
            "ORDERNAME": "46215"
          },
          {
            "NAME": "영광군",
            "CODE": 46225,
            "ORDERNAME": "46225"
          },
          {
            "NAME": "함평군",
            "CODE": 46235,
            "ORDERNAME": "46235"
          },
          {
            "NAME": "신안군",
            "CODE": 46245,
            "ORDERNAME": "46245"
          }
        ]
      },
      {
        "consti_list": [
          {
            "NAME": "경북",
            "CODE": 34700000
          }
        ],
        "town_dict_ORDERNAME": {
          "구미시갑": 47094,
          "경주시갑": 47044,
          "김천시": 47064,
          "안동시을": 47081,
          "문경시": 47144,
          "포항시북구": 47013,
          "예천군": 47155,
          "영천시": 47124,
          "청송군": 47235,
          "경산시": 47164,
          "고령군": 47185,
          "칠곡군": 47215,
          "영주시": 47114,
          "영양군": 47255,
          "군위군": 47205,
          "경주시을": 47051,
          "봉화군": 47265,
          "울릉군": 47035,
          "구미시을": 47101,
          "성주군": 47195,
          "포항시남구": 47020,
          "울진군": 47275,
          "의성군": 47225,
          "영덕군": 47245,
          "상주시": 47134,
          "청도군": 47175,
          "안동시갑": 47074
        },
        "town_dict": {
          "구미시갑": 47094,
          "경주시갑": 47044,
          "김천시": 47064,
          "안동시을": 47081,
          "문경시": 47144,
          "포항시북구": 47013,
          "예천군": 47155,
          "영천시": 47124,
          "청송군": 47235,
          "경산시": 47164,
          "고령군": 47185,
          "칠곡군": 47215,
          "영주시": 47114,
          "영양군": 47255,
          "군위군": 47205,
          "경주시을": 47051,
          "봉화군": 47265,
          "울릉군": 47035,
          "구미시을": 47101,
          "성주군": 47195,
          "포항시남구": 4702,
          "울진군": 47275,
          "의성군": 47225,
          "영덕군": 47245,
          "상주시": 47134,
          "청도군": 47175,
          "안동시갑": 47074
        },
        "consti_dict": {
          "경북": [
            34700000
          ]
        },
        "city_code": 47,
        "city_name": "경북",
        "town_list": [
          {
            "NAME": "포항시북구",
            "CODE": 47013,
            "ORDERNAME": "47013"
          },
          {
            "NAME": "포항시남구",
            "CODE": 4702,
            "ORDERNAME": "47020"
          },
          {
            "NAME": "울릉군",
            "CODE": 47035,
            "ORDERNAME": "47035"
          },
          {
            "NAME": "경주시갑",
            "CODE": 47044,
            "ORDERNAME": "47044"
          },
          {
            "NAME": "경주시을",
            "CODE": 47051,
            "ORDERNAME": "47051"
          },
          {
            "NAME": "김천시",
            "CODE": 47064,
            "ORDERNAME": "47064"
          },
          {
            "NAME": "안동시갑",
            "CODE": 47074,
            "ORDERNAME": "47074"
          },
          {
            "NAME": "안동시을",
            "CODE": 47081,
            "ORDERNAME": "47081"
          },
          {
            "NAME": "구미시갑",
            "CODE": 47094,
            "ORDERNAME": "47094"
          },
          {
            "NAME": "구미시을",
            "CODE": 47101,
            "ORDERNAME": "47101"
          },
          {
            "NAME": "영주시",
            "CODE": 47114,
            "ORDERNAME": "47114"
          },
          {
            "NAME": "영천시",
            "CODE": 47124,
            "ORDERNAME": "47124"
          },
          {
            "NAME": "상주시",
            "CODE": 47134,
            "ORDERNAME": "47134"
          },
          {
            "NAME": "문경시",
            "CODE": 47144,
            "ORDERNAME": "47144"
          },
          {
            "NAME": "예천군",
            "CODE": 47155,
            "ORDERNAME": "47155"
          },
          {
            "NAME": "경산시",
            "CODE": 47164,
            "ORDERNAME": "47164"
          },
          {
            "NAME": "청도군",
            "CODE": 47175,
            "ORDERNAME": "47175"
          },
          {
            "NAME": "고령군",
            "CODE": 47185,
            "ORDERNAME": "47185"
          },
          {
            "NAME": "성주군",
            "CODE": 47195,
            "ORDERNAME": "47195"
          },
          {
            "NAME": "군위군",
            "CODE": 47205,
            "ORDERNAME": "47205"
          },
          {
            "NAME": "칠곡군",
            "CODE": 47215,
            "ORDERNAME": "47215"
          },
          {
            "NAME": "의성군",
            "CODE": 47225,
            "ORDERNAME": "47225"
          },
          {
            "NAME": "청송군",
            "CODE": 47235,
            "ORDERNAME": "47235"
          },
          {
            "NAME": "영덕군",
            "CODE": 47245,
            "ORDERNAME": "47245"
          },
          {
            "NAME": "영양군",
            "CODE": 47255,
            "ORDERNAME": "47255"
          },
          {
            "NAME": "봉화군",
            "CODE": 47265,
            "ORDERNAME": "47265"
          },
          {
            "NAME": "울진군",
            "CODE": 47275,
            "ORDERNAME": "47275"
          }
        ]
      },
      {
        "consti_list": [
          {
            "NAME": "경남",
            "CODE": 34800000
          }
        ],
        "town_dict_ORDERNAME": {
          "진해시": 48074,
          "함양군": 48205,
          "창원시갑": 48014,
          "창원시을": 48021,
          "산청군": 48215,
          "거창군": 48225,
          "통영시": 48084,
          "합천군": 48235,
          "사천시": 48104,
          "마산시합포구": 48033,
          "진주시을": 48061,
          "밀양시": 48124,
          "진주시갑": 48054,
          "김해시": 48114,
          "하동군": 48185,
          "의령군": 48145,
          "창녕군": 48165,
          "남해군": 48195,
          "고성군": 48095,
          "함안군": 48155,
          "마산시회원구": 48040,
          "거제시": 48134,
          "양산시": 48174
        },
        "town_dict": {
          "진해시": 48074,
          "함양군": 48205,
          "창원시갑": 48014,
          "창원시을": 48021,
          "산청군": 48215,
          "거창군": 48225,
          "통영시": 48084,
          "합천군": 48235,
          "사천시": 48104,
          "마산시합포구": 48033,
          "진주시을": 48061,
          "밀양시": 48124,
          "진주시갑": 48054,
          "김해시": 48114,
          "하동군": 48185,
          "의령군": 48145,
          "창녕군": 48165,
          "남해군": 48195,
          "고성군": 48095,
          "함안군": 48155,
          "마산시회원구": 4804,
          "거제시": 48134,
          "양산시": 48174
        },
        "consti_dict": {
          "경남": [
            34800000
          ]
        },
        "city_code": 48,
        "city_name": "경남",
        "town_list": [
          {
            "NAME": "창원시갑",
            "CODE": 48014,
            "ORDERNAME": "48014"
          },
          {
            "NAME": "창원시을",
            "CODE": 48021,
            "ORDERNAME": "48021"
          },
          {
            "NAME": "마산시합포구",
            "CODE": 48033,
            "ORDERNAME": "48033"
          },
          {
            "NAME": "마산시회원구",
            "CODE": 4804,
            "ORDERNAME": "48040"
          },
          {
            "NAME": "진주시갑",
            "CODE": 48054,
            "ORDERNAME": "48054"
          },
          {
            "NAME": "진주시을",
            "CODE": 48061,
            "ORDERNAME": "48061"
          },
          {
            "NAME": "진해시",
            "CODE": 48074,
            "ORDERNAME": "48074"
          },
          {
            "NAME": "통영시",
            "CODE": 48084,
            "ORDERNAME": "48084"
          },
          {
            "NAME": "고성군",
            "CODE": 48095,
            "ORDERNAME": "48095"
          },
          {
            "NAME": "사천시",
            "CODE": 48104,
            "ORDERNAME": "48104"
          },
          {
            "NAME": "김해시",
            "CODE": 48114,
            "ORDERNAME": "48114"
          },
          {
            "NAME": "밀양시",
            "CODE": 48124,
            "ORDERNAME": "48124"
          },
          {
            "NAME": "거제시",
            "CODE": 48134,
            "ORDERNAME": "48134"
          },
          {
            "NAME": "의령군",
            "CODE": 48145,
            "ORDERNAME": "48145"
          },
          {
            "NAME": "함안군",
            "CODE": 48155,
            "ORDERNAME": "48155"
          },
          {
            "NAME": "창녕군",
            "CODE": 48165,
            "ORDERNAME": "48165"
          },
          {
            "NAME": "양산시",
            "CODE": 48174,
            "ORDERNAME": "48174"
          },
          {
            "NAME": "하동군",
            "CODE": 48185,
            "ORDERNAME": "48185"
          },
          {
            "NAME": "남해군",
            "CODE": 48195,
            "ORDERNAME": "48195"
          },
          {
            "NAME": "함양군",
            "CODE": 48205,
            "ORDERNAME": "48205"
          },
          {
            "NAME": "산청군",
            "CODE": 48215,
            "ORDERNAME": "48215"
          },
          {
            "NAME": "거창군",
            "CODE": 48225,
            "ORDERNAME": "48225"
          },
          {
            "NAME": "합천군",
            "CODE": 48235,
            "ORDERNAME": "48235"
          }
        ]
      },
      {
        "consti_list": [
          {
            "NAME": "제주",
            "CODE": 34900000
          }
        ],
        "town_dict_ORDERNAME": {
          "서귀포시": 49034,
          "남제주군": 49045,
          "북제주군": 49025,
          "제주시": 49014
        },
        "town_dict": {
          "서귀포시": 49034,
          "남제주군": 49045,
          "북제주군": 49025,
          "제주시": 49014
        },
        "consti_dict": {
          "제주": [
            34900000
          ]
        },
        "city_code": 49,
        "city_name": "제주",
        "town_list": [
          {
            "NAME": "제주시",
            "CODE": 49014,
            "ORDERNAME": "49014"
          },
          {
            "NAME": "북제주군",
            "CODE": 49025,
            "ORDERNAME": "49025"
          },
          {
            "NAME": "서귀포시",
            "CODE": 49034,
            "ORDERNAME": "49034"
          },
          {
            "NAME": "남제주군",
            "CODE": 49045,
            "ORDERNAME": "49045"
          }
        ]
      }
    ],
    "election_type": "local-pa",
    "nth": 2
  }
]